jsonpointerparse.py
jsonpointerparse-0.1.0.dist-info/METADATA
jsonpointerparse-0.1.0.dist-info/WHEEL
jsonpointerparse-0.1.0.dist-info/licenses/LICENSE
jsonpointerparse-0.1.0.dist-info/RECORD
